[{"songs": ["6 Summers", "Saviers Road"], "artists": ["Anderson .Paak", "Anderson .Paak"], "centerDistance": 0.8549085000000001, "angle": 1.1311806956406913, "color": [0, 0]}, {"songs": ["BagBak", "all my friends", "Sin (feat. Jaden Smith)", "Lean Wit Me"], "artists": ["Vince Staples", "21 Savage", "Young Thug", "Juice WRLD"], "centerDistance": 0.883417275, "angle": 2.3505729243515567, "color": [1, 0]}, {"songs": ["RENTAL", "Kids See Ghosts (feat. Yasiin Bey)", "3005", "IV. Sweatpants"], "artists": ["BROCKHAMPTON", "Kids See Ghosts", "Childish Gambino", "Childish Gambino"], "centerDistance": 0.6223245, "angle": 3.5699651530624226, "color": [2, 0]}, {"songs": ["JOHNNY", "Freeee (Ghost Town, Pt. 2) [feat. Ty Dolla $ign]", "Thug Tears", "Bound 2", "Come Back Baby", "Real Friends", "Garden Shed", "u", "i", "All This Money", "No Role Modelz", "Photosynthesis", "Calligraphy", "Skrawberries (feat. BJ The Chicago Kid)", "Outside!", "S on Ya Chest", "Devastated", "Lucid Dreams", "Wet Dreamz", "20 Min"], "artists": ["BROCKHAMPTON", "Kids See Ghosts", "JPEGMAFIA", "Kanye West", "Pusha T", "Kanye West", "Tyler, the Creator", "Kendrick Lamar", "Kendrick Lamar", "Injury Reserve", "J. Cole", "Saba", "Saba", "Jid", "Vince Staples", "Injury Reserve", "Joey Bada$$", "Juice WRLD", "J. Cole", "LIL UZI VERT"], "centerDistance": 0.7968681500000001, "angle": 4.8006005134548655, "color": [3, 0]}, {"songs": ["DR. WHOEVER", "Spice Girl"], "artists": ["Amin\u00e9", "Amin\u00e9"], "centerDistance": 0.835295, "angle": 6.194973774109411, "color": [4, 0]}]