[{"songs": ["Freshman List", "Dark Knight Dummo (feat. Travis Scott)", "Myself", "Neighbor (feat. Travis Scott)", "No More (feat. Travis Scott, Kodak Black & 21 Savage)", "Love Hurts (feat. Travis Scott)", "Portland", "Talk To Me (with Rich The Kid)", "Nonstop", "Pull Up (feat. NAV)", "Ghostface Killers (feat. Travis Scott)", "4 AM", "Antidote", "FeRRis WhEEL (feat. Trippie Redd)", "can't leave without it", "Kelly Price (feat. Travis Scott)", "Rich and Blind", "Drowning (feat. Kodak Black)", "Never Catch Me", "Moonlight"], "artists": ["NAV", "Trippie Redd", "NAV", "Juicy J", "Metro Boomin", "Playboi Carti", "Drake", "Tory Lanez", "Drake", "A Boogie Wit da Hoodie", "21 Savage, Offset & Metro Boomin", "2 Chainz", "Travi$ Scott", "Tory Lanez", "21 Savage", "Migos", "Juice WRLD", "A Boogie Wit da Hoodie", "Travi$ Scott", "xxxtentacion"], "centerDistance": 0.4410619499999999, "angle": 3.6028193566226085, "color": [0, 0]}, {"songs": ["Yikes", "Psycho (feat. Ty Dolla $ign)", "Sundress", "i"], "artists": ["Kanye West", "Post Malone", "A$AP Rocky", "lil skies"], "centerDistance": 0.6980675000000001, "angle": 4.7795081456816675, "color": [1, 0]}, {"songs": ["Space Cadet (feat. Gunna)", "Shake It Up", "Lean Wit Me", "monster", "KIKA (feat. Tory Lanez)"], "artists": ["Metro Boomin", "Trippie Redd", "Juice WRLD", "21 Savage", "6ix9ine"], "centerDistance": 0.4382446, "angle": 6.216066141882608, "color": [2, 0]}, {"songs": ["First Off (feat. Travis Scott)", "Legacy (feat. Travis Scott & 21 Savage)"], "artists": ["Future", "Offset"], "centerDistance": 0.46599050000000003, "angle": 1.165525613211642, "color": [3, 0]}, {"songs": ["Pretty Little Fears (feat. J. Cole)", "Switch", "Rambo", "Right My Wrongs"], "artists": ["6LACK", "6LACK", "Bryson Tiller", "Bryson Tiller"], "centerDistance": 0.6229359999999999, "angle": 2.4546955491958062, "color": [4, 0]}]