[{"songs": ["Let's Be Friends", "Ready or Not"], "artists": ["Emily Osment", "Bridgit Mendler"], "centerDistance": 0.35332050000000004, "angle": 4.780986653791943, "color": [0, 0]}, {"songs": ["Your Love Is My Drug", "Circus", "Keeps Gettin' Better"], "artists": ["Ke$ha", "Britney Spears", "Christina Aguilera"], "centerDistance": 0.8396509999999999, "angle": 6.214587633772333, "color": [1, 0]}, {"songs": ["Army of Love", "Who Owns My Heart"], "artists": ["Kerli", "Miley Cyrus"], "centerDistance": 0.8262995, "angle": 1.1437984083925459, "color": [2, 0]}, {"songs": ["Crank It Up", "With Love", "Reach Out"], "artists": ["Ashley Tisdale", "Hilary Duff", "Hilary Duff"], "centerDistance": 0.8060243333333332, "angle": 2.356194490192344, "color": [3, 0]}, {"songs": ["All the Boys Want", "Come & Get It", "Blow", "Can't Be Tamed", "Masquerade", "Just in Love", "Top of the World", "Birthday", "Who Says", "How I Roll", "When the Sun Goes Down", "Neon Lights", "Gravity", "En el Amor Hay Que Perdonar", "American Girl", "Love Is a Suicide", "Wonderland", "Beat of My Drum", "Poison", "Unbroken"], "artists": ["Emily Osment", "Selena Gomez", "Ke$ha", "Miley Cyrus", "Ashley Tisdale", "Joe Jonas", "Bridgit Mendler", "Selena Gomez", "Selena Gomez & the Scene", "Britney Spears", "Selena Gomez & the Scene", "Demi Lovato", "Pixie Lott", "Belinda", "Bonnie McKee", "Natalia Kills", "Natalia Kills", "Nicola Roberts", "Nicole Scherzinger", "Demi Lovato"], "centerDistance": 0.81005845, "angle": 3.568590571992143, "color": [4, 0]}]