[{"songs": ["when the sun goes down", "a certain romance", "my mistakes were made for you", "standing next to me", "it's hard to get around the wind", "take me out", "what you know", "no you girls", "fire", "club foot", "a-punk", "crystalised", "diane young", "let's dance to joy division", "something good can work", "come a little closer", "ruby", "breezeblocks", "i would do anything for you", "post break-up sex", "rearrange", "the suburbs", "ready to start", "afraid", "banquet", "come closer", "shake me down", "my number", "islands", "helicopter", "slow hands", "coming of age"], "artists": ["arctic monkeys", "arctic monkeys", "the last shadow puppets", "the last shadow puppets", "alex turner", "franz ferdinand", "two door cinema club", "franz ferdinand", "kasabian", "kasabian", "vampire weekend", "the xx", "vampire weekend", "the wombats", "two door cinema club", "cage the elephant", "kaiser chiefs", "alt-j", "foster the people", "the vaccines", "miles kane", "arcade fire", "arcade fire", "the neighbourhood", "bloc party", "miles kane", "cage the elephant", "foals", "the xx", "bloc party", "interpol", "foster the people"], "centerDistance": 0.7673282812500001, "angle": 4.43005612117082, "color": [0, 0]}, {"songs": ["on top of the world", "demons"], "artists": ["imagine dragons", "imagine dragons"], "centerDistance": 0.8563430000000001, "angle": 0.2823328592138692, "color": [1, 0]}, {"songs": ["someday", "reptilia", "mr. brightside", "when you were young", "sex on fire", "use somebody", "evil"], "artists": ["the strokes", "the strokes", "the killers", "the killers", "kings of leon", "kings of leon", "interpol"], "centerDistance": 0.7830348571428571, "angle": 1.420237533145185, "color": [2, 0]}, {"songs": ["sex", "girls"], "artists": ["the 1975", "the 1975"], "centerDistance": 0.8602345, "angle": 2.1587463509036198, "color": [2, 1]}, {"songs": ["she moves in her own way", "seaside", "if you wanna", "chelsea dagger", "can't stand me now", "whistle for the choir", "time for heroes"], "artists": ["the kooks", "the kooks", "the vaccines", "the fratellis", "the libertines", "the fratellis", "the libertines"], "centerDistance": 0.7925571428571431, "angle": 3.2303560018944317, "color": [3, 0]}]