[{"songs": ["Shoota (feat. Lil Uzi Vert)"], "artists": ["Playboi Carti"], "centerDistance": 0.23101499999999997, "angle": 1.146709081548285, "color": [0, 0]}, {"songs": ["What Would Meek Do? (feat. Kanye West)"], "artists": ["Pusha T"], "centerDistance": 0.47639600000000004, "angle": 2.3503547922891292, "color": [1, 0]}, {"songs": ["911 / Mr. Lonely (feat. Frank Ocean and Steve Lacy)", "Purity (feat. Frank Ocean)", "Smuckers (feat. Lil Wayne and Kanye West)", "New earlsweatshirt (Interlude)", "Praise The Lord (Da Shine) [feat. Skepta]", "Telephone Calls (feat. A$AP Rocky, Tyler, the Creator, Playboi Carti & Yung Gleesh)", "Raf (feat. A$AP Rocky, Playboi Carti, Quavo, Lil Uzi Vert & Frank Ocean)", "Ghost Town (feat. PARTYNEXTDOOR)", "Father Stretch My Hands, Pt. 1", "New Choppa (feat. A$AP Rocky)", "NOWHERE2GO", "Overdue (feat. Travis Scott)", "Sunday (feat. Frank Ocean)", "CLOUT COBAIN l CLOUT CO13A1N", "4th Dimension (feat. Louis Prima)", "Freeee (Ghost Town, Pt. 2) [feat. Ty Dolla $ign]", "BLACK BALLOONS l 13LACK 13ALLOONZ (feat. Twelve'len & GoldLink)", "InFInItY (888) [fEaT. jOeY bAdA$$]", "Pursuit of Happiness (Nightmare) [feat. MGMT & Ratatat]", "Survival Tactics (feat. Capital Steez)"], "artists": ["Tyler, the Creator", "A$AP Rocky", "Tyler, the Creator", "Vince Staples", "A$AP Rocky", "A$AP Mob", "A$AP Mob", "Kanye West", "Kanye West", "Playboi Carti", "Earl Sweatshirt", "Metro Boomin", "Earl Sweatshirt", "Denzel Curry", "Kids See Ghosts", "Kids See Ghosts", "Denzel Curry", "xxxtentacion", "Kid Cudi", "Joey Bada$$"], "centerDistance": 0.25462185, "angle": 3.565679898836404, "color": [2, 0]}, {"songs": ["10 Freaky Girls (feat. 21 Savage)"], "artists": ["Metro Boomin"], "centerDistance": 0.27300899999999995, "angle": 4.781005005383678, "color": [3, 0]}, {"songs": ["New Orleans", "Nuketown (feat. Juice WRLD)", "151 Rum"], "artists": ["BROCKHAMPTON", "SKI MASK THE SLUMP GOD", "Jid"], "centerDistance": 0.5001403333333333, "angle": 6.214569282180597, "color": [4, 0]}]